__init__.py
yaltapy/__init__.py
yaltapy/arrange_table.py
yaltapy/chain_poles_poly.py
yaltapy/cline.py
yaltapy/comparator_min.py
yaltapy/comparator_min_test_pva.py
yaltapy/compute_pade.py
yaltapy/compute_tf.py
yaltapy/crossing_table.py
yaltapy/data.py
yaltapy/error_eval.py
yaltapy/error_eval_phase.py
yaltapy/eval_compare_func_min.py
yaltapy/eval_diff.py
yaltapy/extend_poly.py
yaltapy/final_min.py
yaltapy/fminbnd.py
yaltapy/frac_theta.py
yaltapy/get_pade_coeff.py
yaltapy/get_roots_error.py
yaltapy/get_tau_real_root.py
yaltapy/imag_axis_chain.py
yaltapy/integrate_unstable_poles_min.py
yaltapy/norm_inf.py
yaltapy/order_vec.py
yaltapy/parameters.py
yaltapy/phase.py
yaltapy/poly_vect_der.py
yaltapy/power_poly.py
yaltapy/predictor.py
yaltapy/pva.py
yaltapy/reduce_deg_poly.py
yaltapy/roots_looper.py
yaltapy/simplify_system.py
yaltapy/stability_chains.py
yaltapy/stability_windows.py
yaltapy/system_type.py
yaltapy/thread_analysis.py
yaltapy/thread_root_locus.py
yaltapy/thread_stability_windows.py
yaltapy/decorators/__init__.py
yaltapy/decorators/control_inputs.py
yaltapy-1.0.0.dist-info/METADATA
yaltapy-1.0.0.dist-info/WHEEL
yaltapy-1.0.0.dist-info/top_level.txt
yaltapy-1.0.0.dist-info/RECORD
