Metadata-Version: 2.1
Name: yaltapy
Version: 1.0.0
Summary: Python module for the study analysis of (fractional) delayed systems given by their transfer function.
Author: Hugo Cavalera
Author-email: Catherine Bonnet <catherine.bonnet@inria.fr>, Guilherme Mazanti <guilherme.mazanti@inria.fr>
License: GNU General Public License v3 (GPLv3)
Project-URL: Homepage, https://project.inria.fr/yalta/
Project-URL: Source, https://gitlab.inria.fr/disco/yaltapy-public
Project-URL: Bug Tracker, https://gitlab.inria.fr/disco/yaltapy-public/-/issues
Classifier: Programming Language :: Python :: 3.7
Classifier: Programming Language :: Python :: 3.8
Classifier: Programming Language :: Python :: 3.9
Classifier: Programming Language :: Python :: 3.10
Classifier: License :: OSI Approved :: GNU General Public License v3 (GPLv3)
Classifier: Operating System :: OS Independent
Classifier: Development Status :: 5 - Production/Stable
Classifier: Intended Audience :: Science/Research
Classifier: Topic :: Scientific/Engineering
Classifier: Topic :: Scientific/Engineering :: Mathematics
Requires-Python: >=3.7
Requires-Dist: control (>=0.8.4)
Requires-Dist: matplotlib (>=3.0.0)
Requires-Dist: numpy (>=1.20.1)
Requires-Dist: scipy (>=1.6.0)
